How2jDisanfangKaifaJiaochengShijianXiangmuMianshiti/README.md
How2jDisanfangKaifaJiaochengShijianXiangmuMianshiti/__init__.py
How2jDisanfangKaifaJiaochengShijianXiangmuMianshiti/__main__.py
How2jDisanfangKaifaJiaochengShijianXiangmuMianshiti/file.epub
How2jDisanfangKaifaJiaochengShijianXiangmuMianshiti/index.html
How2jDisanfangKaifaJiaochengShijianXiangmuMianshiti/css/__init__.py
How2jDisanfangKaifaJiaochengShijianXiangmuMianshiti/css/annotations.css
How2jDisanfangKaifaJiaochengShijianXiangmuMianshiti/css/main.css
How2jDisanfangKaifaJiaochengShijianXiangmuMianshiti/css/normalize.css
How2jDisanfangKaifaJiaochengShijianXiangmuMianshiti/css/popup.css
How2jDisanfangKaifaJiaochengShijianXiangmuMianshiti/font/__init__.py
How2jDisanfangKaifaJiaochengShijianXiangmuMianshiti/font/fontello.eot
How2jDisanfangKaifaJiaochengShijianXiangmuMianshiti/font/fontello.svg
How2jDisanfangKaifaJiaochengShijianXiangmuMianshiti/font/fontello.ttf
How2jDisanfangKaifaJiaochengShijianXiangmuMianshiti/font/fontello.woff
How2jDisanfangKaifaJiaochengShijianXiangmuMianshiti/img/__init__.py
How2jDisanfangKaifaJiaochengShijianXiangmuMianshiti/img/annotator-glyph-sprite.png
How2jDisanfangKaifaJiaochengShijianXiangmuMianshiti/img/annotator-icon-sprite.png
How2jDisanfangKaifaJiaochengShijianXiangmuMianshiti/img/apple-touch-icon.png
How2jDisanfangKaifaJiaochengShijianXiangmuMianshiti/img/cancelfullscreen.png
How2jDisanfangKaifaJiaochengShijianXiangmuMianshiti/img/close.png
How2jDisanfangKaifaJiaochengShijianXiangmuMianshiti/img/fullscreen.png
How2jDisanfangKaifaJiaochengShijianXiangmuMianshiti/img/loader.gif
How2jDisanfangKaifaJiaochengShijianXiangmuMianshiti/img/menu-icon.png
How2jDisanfangKaifaJiaochengShijianXiangmuMianshiti/img/save.png
How2jDisanfangKaifaJiaochengShijianXiangmuMianshiti/img/saved.png
How2jDisanfangKaifaJiaochengShijianXiangmuMianshiti/img/settings-s.png
How2jDisanfangKaifaJiaochengShijianXiangmuMianshiti/img/settings.png
how2j_disanfang_kaifa_jiaocheng_shijian_xiangmu_mianshiti-2024.3.5.0.dist-info/METADATA
how2j_disanfang_kaifa_jiaocheng_shijian_xiangmu_mianshiti-2024.3.5.0.dist-info/WHEEL
how2j_disanfang_kaifa_jiaocheng_shijian_xiangmu_mianshiti-2024.3.5.0.dist-info/entry_points.txt
how2j_disanfang_kaifa_jiaocheng_shijian_xiangmu_mianshiti-2024.3.5.0.dist-info/top_level.txt
how2j_disanfang_kaifa_jiaocheng_shijian_xiangmu_mianshiti-2024.3.5.0.dist-info/RECORD
